rabbitmqpy/__init__.py
rabbitmqpy/log_publish.py
rabbitmqpy/log_subscribe.py
rabbitmqpy/publish.py
rabbitmqpy/subscribe.py
rabbitmqpy-0.1.3.dist-info/LICENSE
rabbitmqpy-0.1.3.dist-info/METADATA
rabbitmqpy-0.1.3.dist-info/WHEEL
rabbitmqpy-0.1.3.dist-info/top_level.txt
rabbitmqpy-0.1.3.dist-info/RECORD
