Metadata-Version: 2.1
Name: rabbitmqpy
Version: 0.1.3
Summary: A simple Python library for easily connect to rabbitmq.
Home-page: https://gitee.com/zsq_tee/rabbitmqpy
Author: Shuiqing Zheng
Author-email: shuiqingzheng@126.com
License: MIT
Project-URL: Documentation, https://gitee.com/zsq_tee/rabbitmqpy
Project-URL: Source, https://gitee.com/zsq_tee/rabbitmqpy
Requires-Python: >=3.6
License-File: LICENSE
